go_smp/__init__.py
go_smp/_bindings.py
go_smp/_gosmp.cpython-313-x86_64-linux-gnu.so
go_smp-0.1.1.dist-info/METADATA
go_smp-0.1.1.dist-info/WHEEL
go_smp-0.1.1.dist-info/top_level.txt
go_smp-0.1.1.dist-info/RECORD
go_smp-0.1.1.dist-info/licenses/LICENCE
