Metadata-Version: 2.4
Name: go-smp
Version: 0.1.1
Summary: Python bindings for the aws tool session-manager-plugin
Author-email: Simon Fletcher <simon.fletcher@lexisnexisrisk.com>
Project-URL: Homepage, https://github.com/simonfletcher-ln/go-smp
Project-URL: Repository, https://github.com/simonfletcher-ln/go-smp
Classifier: Programming Language :: Python :: 3
Classifier: Operating System :: OS Independent
Requires-Python: >=3.13
License-File: LICENCE
Dynamic: license-file
